conversor_divisor/__init__.py
conversor_divisor/app.py
conversor_divisor/convert.py
conversor_divisor/functions.py
conversor_divisor/resources.py
conversor_divisor/settings.py
conversor_divisor/ui.py
conversor_divisor/worker.py
conversor_divisor/FFmpeg/LICENSE.txt
conversor_divisor/FFmpeg/README.md
conversor_divisor/FFmpeg/README.txt
conversor_divisor/FFmpeg/bin/ffmpeg.exe
conversor_divisor/HandBrakeCLI/HandBrakeCLI.exe
conversor_divisor/HandBrakeCLI/README.md
conversor_divisor/MP4Box/Changelog.txt
conversor_divisor/MP4Box/GPAX.dll
conversor_divisor/MP4Box/GdiPlus.dll
conversor_divisor/MP4Box/License.txt
conversor_divisor/MP4Box/OpenSVCDecoder.dll
conversor_divisor/MP4Box/Osmo4.exe
conversor_divisor/MP4Box/README.md
conversor_divisor/MP4Box/ReadMe.txt
conversor_divisor/MP4Box/avcodec-55.dll
conversor_divisor/MP4Box/avdevice-55.dll
conversor_divisor/MP4Box/avfilter-4.dll
conversor_divisor/MP4Box/avformat-55.dll
conversor_divisor/MP4Box/avresample-1.dll
conversor_divisor/MP4Box/avutil-52.dll
conversor_divisor/MP4Box/configuration.html
conversor_divisor/MP4Box/dashcast.exe
conversor_divisor/MP4Box/gm_aac_in.dll
conversor_divisor/MP4Box/gm_ac3_in.dll
conversor_divisor/MP4Box/gm_bifs_dec.dll
conversor_divisor/MP4Box/gm_ctx_load.dll
conversor_divisor/MP4Box/gm_dummy_in.dll
conversor_divisor/MP4Box/gm_dx_hw.dll
conversor_divisor/MP4Box/gm_ffmpeg_in.dll
conversor_divisor/MP4Box/gm_ft_font.dll
conversor_divisor/MP4Box/gm_gdip_raster.dll
conversor_divisor/MP4Box/gm_gpac_js.dll
conversor_divisor/MP4Box/gm_img_in.dll
conversor_divisor/MP4Box/gm_ismacryp.dll
conversor_divisor/MP4Box/gm_isom_in.dll
conversor_divisor/MP4Box/gm_laser_dec.dll
conversor_divisor/MP4Box/gm_mp3_in.dll
conversor_divisor/MP4Box/gm_mpd_in.dll
conversor_divisor/MP4Box/gm_mpegts_in.dll
conversor_divisor/MP4Box/gm_mse_in.dll
conversor_divisor/MP4Box/gm_odf_dec.dll
conversor_divisor/MP4Box/gm_ogg.dll
conversor_divisor/MP4Box/gm_openhevc_dec.dll
conversor_divisor/MP4Box/gm_opensvc_dec.dll
conversor_divisor-3.3.3.dist-info/LICENSE
conversor_divisor-3.3.3.dist-info/METADATA
conversor_divisor-3.3.3.dist-info/WHEEL
conversor_divisor-3.3.3.dist-info/entry_points.txt
conversor_divisor-3.3.3.dist-info/top_level.txt
conversor_divisor-3.3.3.dist-info/RECORD
