Metadata-Version: 2.1
Name: conversor-divisor
Version: 3.3.3
Summary: software for converting and splitting medias
Home-page: https://github.com/hadtrindade/conversor-e-divisor
Author: Ivo H. Trindade Silva
Author-email: haddleytrindade@gmail.com
License: MIT
Keywords: GUI for converting and splitting medias using ffmpeg and mp4box
Platform: any
Classifier: Environment :: Console
Classifier: License :: OSI Approved :: MIT License
Classifier: Operating System :: OS Independent
Classifier: Programming Language :: Python :: 3.10
Classifier: Framework :: Pytest
Requires-Python: >=3.8
License-File: LICENSE
Requires-Dist: PySide2
Requires-Dist: toml
Provides-Extra: dev
Requires-Dist: flake8 ; extra == 'dev'
Requires-Dist: pytest ; extra == 'dev'
Requires-Dist: pytest-cov ; extra == 'dev'
Requires-Dist: pytest-mock ; extra == 'dev'
Requires-Dist: pytest-qt ; extra == 'dev'
Requires-Dist: blue ; extra == 'dev'
Requires-Dist: isort ; extra == 'dev'
Requires-Dist: PySide2 ; extra == 'dev'
Requires-Dist: toml ; extra == 'dev'
Requires-Dist: pyinstaller ; extra == 'dev'
